README.rst
setup.py
lfs_ipsum/__init__.py
lfs_ipsum.egg-info/PKG-INFO
lfs_ipsum.egg-info/SOURCES.txt
lfs_ipsum.egg-info/dependency_links.txt
lfs_ipsum.egg-info/not-zip-safe
lfs_ipsum.egg-info/requires.txt
lfs_ipsum.egg-info/top_level.txt
lfs_ipsum/management/__init__.py
lfs_ipsum/management/commands/__init__.py
lfs_ipsum/management/commands/generate_categories.py