Metadata-Version: 1.1
Name: lfs-ipsum
Version: 0.1
Summary: Content generator for LFS
Home-page: http://github.com/tzicatl/lfs_ipsum
Author: Noe Nieto
Author-email: nnieto@noenieto.com
License: BSD
Keywords: django e-commerce online-shop lorem ipsum
Platform: UNKNOWN
Classifier: Environment :: Web Environment
Classifier: Framework :: Django
Classifier: License :: OSI Approved :: BSD License
Classifier: Operating System :: OS Independent
Classifier: Programming Language :: Python
